tibber_local_lib/__init__.py
tibber_local_lib/decoder.py
tibber_local_lib-1.3.0.dist-info/LICENSE
tibber_local_lib-1.3.0.dist-info/METADATA
tibber_local_lib-1.3.0.dist-info/WHEEL
tibber_local_lib-1.3.0.dist-info/top_level.txt
tibber_local_lib-1.3.0.dist-info/RECORD
