Metadata-Version: 2.1
Name: tibber_local_lib
Version: 1.3.0
Summary: A library to fetch and decode SML data locally from Tibber Pulse
Home-page: https://github.com/SonnenladenGmbH/tibber_local_lib
Author: Leo Tiedt | Sonnenladen GmbH
Author-email: l.tiedt@sonnenladen.de
Classifier: Programming Language :: Python :: 3
Classifier: License :: OSI Approved :: MIT License
Classifier: Operating System :: OS Independent
Requires-Python: >=3.6
License-File: LICENSE
Requires-Dist: requests
Requires-Dist: smllib
